
{
    "@context": "http://schema.org",
    "@type": "Blog",
    "blogPost": {
        "@type": "BlogPosting",
        "dateCreated":"2017-01-26T13:30:00+08:00",
        "dateModified":"2017-02-06T03:00:00+08:00",
        "datePublished":"2017-02-06T03:00:00+08:00",
        "headline": "Submitting website to crawlers and adding to business listing services",
        "description": "Search engine crawlers accept website submitted to it manually and can crawl from it. Business listing services helps making website visible in the local area.",
        "mainEntityOfPage": {
            "@type": "WebPage",
            "@id": "https://www.google.com/webmasters/tools/home"
        },
        "author": {
            "@type": "Person",
            "name": "SlowTick",
            "email": "slowtick@hotmail.com"
        },
        "publisher": {
            "@type": "Organization",
            "name": "SlowTick",
            "email": "slowtick@hotmail.com",
            "logo": {
                "@type": "ImageObject",
                "url": "http://www.slowtick.com/assets/images/slowtick.png",
                "width": 32,
                "height": 32
            }
        },
        "url": "http://www.slowtick.com/pages/getting-site-crawled.html",
        "image": {
            "@type": "ImageObject",
            "url": "http://www.slowtick.com/assets/images/away-1991860_1920.jpg",
            "width": 1638,
            "height": 1920
        },
        "license": "https://creativecommons.org/licenses/by/4.0/"
    }
}
